ff_arq/__init__.py
ff_arq/decorator.py
ff_arq/schema.py
ff_arq/task_manager.py
ff_arq/task_queue.py
ff_arq/task_worker.py
ff_arq-0.1.0.dist-info/METADATA
ff_arq-0.1.0.dist-info/WHEEL
ff_arq-0.1.0.dist-info/top_level.txt
ff_arq-0.1.0.dist-info/RECORD
