Metadata-Version: 2.1
Name: ff-arq
Version: 0.1.0
Summary: A simple arq library.
Home-page: https://github.com/itsanr-oris/ff-arq
Author: foris.feng
Author-email: us@f-oris.me
License: MIT
Project-URL: Bug Tracker, https://github.com/itsanr-oris/ff-arq/issues
Project-URL: Source Code, https://github.com/itsanr-oris/ff-arq
Keywords: arq,redis-queue
Classifier: Programming Language :: Python :: 3
Classifier: Programming Language :: Python :: 3.6
Classifier: Programming Language :: Python :: 3.7
Classifier: Programming Language :: Python :: 3.8
Classifier: Programming Language :: Python :: 3.9
Classifier: Programming Language :: Python :: 3.10
Classifier: Programming Language :: Python :: 3.11
Classifier: Programming Language :: Python :: 3.12
Classifier: Programming Language :: Python :: 3.13
Classifier: License :: OSI Approved :: MIT License
Classifier: Operating System :: OS Independent
Requires-Python: >=3.6
Requires-Dist: arq
Requires-Dist: redis >=4.2.0
Requires-Dist: typing-extensions ; python_version < "3.10"
Provides-Extra: tests
Requires-Dist: faker ; extra == 'tests'
Requires-Dist: pytest ; extra == 'tests'
Requires-Dist: pytest-cov ; extra == 'tests'
Requires-Dist: pytest-asyncio ; extra == 'tests'
